singleline_models/__init__.py
singleline_models/_modidx.py
singleline_models/dataset.py
singleline_models/sketch_rnn.py
singleline_models/sketch_transformer.py
singleline_models/utils.py
singleline_models/lstm/__init__.py
singleline_models/lstm/all.py
singleline_models/lstm/custom_lstm.py
singleline_models/lstm/rnnlib.py
singleline_models/lstm/shim.py
singleline_models/sketch_rnn/__init__.py
singleline_models/sketch_rnn/all.py
singleline_models/sketch_rnn/layers.py
singleline_models/sketch_rnn/model.py
singleline_models/sketch_rnn/sampler.py
singleline_models/sketch_rnn/trainer.py
singleline_models/sketch_transformer/__init__.py
singleline_models/sketch_transformer/all.py
singleline_models/sketch_transformer/layers.py
singleline_models/sketch_transformer/masks.py
singleline_models/sketch_transformer/model.py
singleline_models/sketch_transformer/sampler.py
singleline_models/sketch_transformer/trainer.py
sketch_rnn/__init__.py
sketch_rnn/custom_lstms.py
singleline_models-0.0.2.dist-info/LICENSE
singleline_models-0.0.2.dist-info/METADATA
singleline_models-0.0.2.dist-info/WHEEL
singleline_models-0.0.2.dist-info/entry_points.txt
singleline_models-0.0.2.dist-info/top_level.txt
singleline_models-0.0.2.dist-info/RECORD
