Metadata-Version: 2.1
Name: singleline-models
Version: 0.0.2
Summary: ML Models for Single-Line Drawings
Home-page: https://github.com/andrewlook/singleline_models
Author: Andrew Look
Author-email: andrew.m.look@gmail.com
License: Apache Software License 2.0
Keywords: nbdev jupyter notebook python
Platform: UNKNOWN
Classifier: Development Status :: 4 - Beta
Classifier: Intended Audience :: Developers
Classifier: Natural Language :: English
Classifier: Programming Language :: Python :: 3.7
Classifier: Programming Language :: Python :: 3.8
Classifier: Programming Language :: Python :: 3.9
Classifier: Programming Language :: Python :: 3.10
Classifier: License :: OSI Approved :: Apache Software License
Requires-Python: >=3.7
Requires-Dist: fastcore
Requires-Dist: torch
Requires-Dist: numpy
Requires-Dist: matplotlib
Requires-Dist: Pillow
Requires-Dist: einops
Requires-Dist: fastprogress
Requires-Dist: wandb
Requires-Dist: onnx
Requires-Dist: transformers
Provides-Extra: dev
Requires-Dist: jupyterlab ; extra == 'dev'
